dicom4ortho/__init__.py
dicom4ortho/__main__.py
dicom4ortho/config.py
dicom4ortho/controller.py
dicom4ortho/defaults.py
dicom4ortho/m_dent_oip.py
dicom4ortho/m_orthodontic_photograph.py
dicom4ortho/m_orthodontic_radiograph.py
dicom4ortho/m_tooth_codes.py
dicom4ortho/model.py
dicom4ortho/snomed-codes.py
dicom4ortho/utils.py
dicom4ortho/view.py
dicom4ortho/dicom/__init__.py
dicom4ortho/dicom/dimse.py
dicom4ortho/dicom/status_codes.py
dicom4ortho/dicom/wado.py
dicom4ortho/resources/__init__.py
dicom4ortho/resources/codes.csv
dicom4ortho/resources/image_types.csv
dicom4ortho/resources/views.csv
dicom4ortho-0.5.1.dist-info/licenses/LICENSE
dicom4ortho-0.5.1.dist-info/METADATA
dicom4ortho-0.5.1.dist-info/WHEEL
dicom4ortho-0.5.1.dist-info/entry_points.txt
dicom4ortho-0.5.1.dist-info/top_level.txt
dicom4ortho-0.5.1.dist-info/RECORD
