Metadata-Version: 2.4
Name: dicom4ortho
Version: 0.5.1
Summary: A DICOM Implementation for Orthodontic Images
Author-email: Toni Magni <amagni@open-ortho.org>
License: MIT License
Project-URL: homepage, https://github.com/open-ortho/dicom4ortho
Keywords: DICOM,VL,Visible Light Photography,Orthodontics
Classifier: Development Status :: 3 - Alpha
Classifier: Intended Audience :: Developers
Classifier: Intended Audience :: Healthcare Industry
Classifier: Topic :: Scientific/Engineering :: Medical Science Apps.
Classifier: Topic :: Scientific/Engineering :: Image Processing
Classifier: License :: OSI Approved :: MIT License
Classifier: Programming Language :: Python :: 3
Requires-Python: >=3.10
License-File: LICENSE
Requires-Dist: argparse
Requires-Dist: pydicom
Requires-Dist: pynetdicom<3,>=2
Requires-Dist: pillow>=9.2.0
Requires-Dist: prettytable
Requires-Dist: numpy
Requires-Dist: urllib3>=1.26.5
Requires-Dist: requests<3.0.0,>=2.32.4
Provides-Extra: dev
Requires-Dist: wrapt; extra == "dev"
Requires-Dist: pylint; extra == "dev"
Requires-Dist: twine; extra == "dev"
Requires-Dist: autopep8; extra == "dev"
Requires-Dist: bumpversion; extra == "dev"
Requires-Dist: pytest; extra == "dev"
Requires-Dist: build; extra == "dev"
Dynamic: license-file
